pcl/__init__.py
pcl/_pcl.cpython-37m-darwin.so
pcl/_pcl.py
pcl/pcl_visualization.cpython-37m-darwin.so
python_pcl-0.3.0a1.dist-info/LICENSE
python_pcl-0.3.0a1.dist-info/METADATA
python_pcl-0.3.0a1.dist-info/WHEEL
python_pcl-0.3.0a1.dist-info/top_level.txt
python_pcl-0.3.0a1.dist-info/RECORD
